computer-organization/alu-design/alu/mux_5x1_32bit.v
// 5-to-1 multiplexer for 32-bit inputs

module mux_5x1_32bit(
    input [31:0] add_result, // Addition result
    input [31:0] sub_result, // Subtraction result
    input [31:0] and_result, // AND result
    input [31:0] xor_result, // XOR result
    input [31:0] slt_result, // Set Less Than result
    input [2:0] select, // 3-bit select line to choose the output
    output reg [31:0] result // 32-bit output for the selected result
);

    always @(*) begin // Always block to evaluate the output based on the select line
        case(select)
            3'b000: result = add_result;  // Add
            3'b001: result = sub_result;  // Subtract
            3'b010: result = and_result;  // AND
            3'b011: result = xor_result;  // XOR
            3'b101: result = slt_result;  // SLT
            default: result = 32'b0;      // Default case to avoid latches
        endcase
    end

endmodule

computer-organization/alu-design/alu-with-regfile/zeroextender_32bit.v
// This module takes a 1-bit input and zero-extends it to a 32-bit output.
// The output will have the 1-bit input in the least significant bit position, and the rest of the bits will be zero.

module zeroextender_32bit(
    input i, // 1-bit input
    output [31:0] o // 32-bit output
);
    assign o = {31'b0, i}; // Zero-extend the 1-bit input to 32 bits
endmodule

computer-organization/alu-design/alu/slt_32bit.v
// 32-bit Set Less Than (SLT) Module
// This module compares two 32-bit inputs and produces a result indicating if the first input is less than the second input

module slt_32bit(
    input msb_a,          // Most significant bit of the first input
    input msb_b,          // Most significant bit of the second input
    input sum_msb,        // Sum of the two inputs (most significant bit)
    input ctrl0,          // ALU Control 0 
    input ctrl1,          // ALU Control 1
    output overflow,      // Overflow   
    output slt_result     // Result of the SLT operation
);
    wire xnor_3_out;      // XNOR operation on the most significant bits and control bit
    wire xor1_out;        // XOR operation between msb_a and sum_msb
    wire not_ctrl1;       // NOT operation on ctrl1
    wire and_3_out;       // AND operation on xnor_3_out, xor1_out, and not_ctrl1

    assign xnor_3_out = ~(msb_a ^ msb_b ^ ctrl0); 
    assign xor1_out = msb_a ^sum_msb; 
    assign not_ctrl1 = ~ctrl1; 
    assign and_3_out = xnor_3_out & xor1_out & not_ctrl1;
    assign overflow = and_3_out;

    assign slt_result = and_3_out ^ sum_msb; // Result of the SLT operation
endmodule

computer-organization/alu-design/alu-with-regfile/xor_32bit.v
// 32-bit XOR gate
// This module takes two 32-bit inputs and performs a bitwise XOR operation

module xor_32bit(
    input [31:0] a, // First 32-bit input
    input [31:0] b, // Second 32-bit input
    output [31:0] result // 32-bit output for the result of the XOR operation
);  
    assign result = a ^ b; // Perform bitwise XOR operation on the inputs
endmodule

computer-organization/alu-design/alu/and_32bit.v
// 32 bit AND gate
// This module takes two 32-bit inputs and performs a bitwise AND operation

module and_32bit(
    input [31:0] a, // First 32-bit input
    input [31:0] b, // Second 32-bit input
    output [31:0] result // 32-bit output for the result of the AND operation
);
    assign result = a & b; // Perform bitwise AND operation on the inputs
endmodule

computer-organization/alu-design/alu/fulladder_32bit.v
// 32-bit Full Adder Module
// This module takes two 32-bit inputs and a carry-in bit, and produces a 32-bit sum and a carry-out bit

module fulladder_32bit(
    input [31:0] a, // First 32-bit input
    input [31:0] b, // Second 32-bit input
    input cin, // Carry-in bit
    output [31:0] sum, // 32-bit output for the sum
    output cout // Carry-out bit
);
    wire [32:0] temp_sum; // Temporary wire to hold the sum and carry-out
    
    assign temp_sum = {1'b0, a} + {1'b0, b} + {32'b0, cin}; // Perform addition of the inputs and carry-in
    assign sum = temp_sum[31:0]; // Assign the lower 32 bits of the result to sum
    assign cout = temp_sum[32]; // Assign the 33rd bit of the result to cout (carry-out)
endmodule

computer-organization/alu-design/alu/alu.v
// Arithmetic Logic Unit (ALU) that works according to the homework requirements.
// This ALU supports addition, subtraction, AND, XOR, and set less than (slt) operations.

module alu(
    input [31:0] a,          // First operand
    input [31:0] b,          // Second operand
    input [2:0] alu_control, // ALU control signal
    
    output [31:0] result,   // ALU result
    output overflow,        // Overflow flag
    output carry            // Carry out flag
);

    // Wire declarations for internal signals
    wire [31:0] add_result, sub_result, and_result, xor_result; // ALU operation results
    wire [31:0] slt_extended; // Extended SLT result
    wire slt_result; // SLT result (1 bit)
    wire msb_a, msb_b, sum_msb; // MSB of operands and result
    wire [31:0] b_inverted; // Inverted b for subtraction
    wire cin_for_sub, cout_add, cout_sub; // Carry out signals for addition and subtraction

    // MSB (Most Significant Bit) of a and b for overflow detection
    assign msb_a = a[31];
    assign msb_b = b[31];
    
    // Full adder for addition
    fulladder_32bit adder(
        .a(a), // First operand
        .b(b), // Second operand
        .cin(1'b0), // Carry-in for addition is 0
        .sum(add_result), // Sum result
        .cout(cout_add) // Carry out for addition
    );
    
    assign b_inverted = ~b; // Inverted b for subtraction
    assign cin_for_sub = 1'b1; // Carry-in for subtraction is 1 (to add 1 after inversion)
    
    // Full adder for subtraction
    fulladder_32bit subtractor(
        .a(a), // First operand
        .b(b_inverted), // Inverted second operand
        .cin(cin_for_sub), // Carry-in for subtraction
        .sum(sub_result), // Subtraction result
        .cout(cout_sub) // Carry out for subtraction
    );
    
    // MSB of the result for overflow detection
    // We check the MSB of the result based on the operation type
    assign sum_msb = (alu_control == 3'b000) ? add_result[31] : sub_result[31];
    
    // AND operation
    and_32bit and_op(
        .a(a), // First operand
        .b(b), // Second operand
        .result(and_result) // AND result
    );
    
    // XOR operation
    xor_32bit xor_op(
        .a(a), // First operand
        .b(b), // Second operand
        .result(xor_result) // XOR result
    );
    
    // SLT (Set if Less Than) operation
    slt_32bit slt_op(
        .msb_a(msb_a), // MSB of first operand
        .msb_b(msb_b), // MSB of second operand
        .sum_msb(sum_msb), // MSB of the addition/subtraction result
        .ctrl0(alu_control[0]), // Control signal for SLT operation
        .ctrl1(alu_control[1]), // Control signal for SLT operation
        .overflow(overflow), // Overflow flag
        .slt_result(slt_result) // SLT result (1 bit)
    );
    
    // Extend SLT result to 32 bits
    zeroextender_32bit slt_extender(
        .i(slt_result), // Input SLT result (1 bit)
        .o(slt_extended) // Output extended SLT result (32 bits)
    );
    
    // Multiplexer to select the final result based on ALU control signal
    mux_5x1_32bit result_mux(
        .add_result(add_result), // Addition result
        .sub_result(sub_result), // Subtraction result
        .and_result(and_result), // AND result
        .xor_result(xor_result), // XOR result
        .slt_result(slt_extended), // Extended SLT result
        .select(alu_control), // ALU control signal to select the operation
        .result(result) // Final ALU result
    );
    
    // Carry out signal assignment based on ALU control signal
    assign carry = (alu_control == 3'b000) ? cout_add : 
                   (alu_control == 3'b001) ? cout_sub : 1'b0;
    
endmodule

computer-organization/alu-design/alu/alu_tb.v
// This is a testbench for the ALU module.

module alu_tb;
    reg [31:0] a, b;         // Input operands
    reg [2:0] alu_control;   // ALU control signal
    wire [31:0] result;      // ALU result
    wire overflow;           // Overflow flag
    wire carry;              // Carry flag

    // Instantiate the ALU module
    alu uut(
        .a(a), // Input operand a
        .b(b), // Input operand b
        .alu_control(alu_control), // ALU control signal
        .result(result), // ALU result
        .overflow(overflow), // Overflow flag
        .carry(carry) // Carry flag
    );
    
    initial begin
        
        $dumpfile("alu.vcd");  
        $dumpvars(0, alu_tb); 

        a = 0; // Initialize input operands
        b = 0; // Initialize input operands
        alu_control = 0; // Initialize ALU control signal
        
        // Wait for the global reset
        #10;
        
        // Test case 1: Addition (alu_control = 000)
        a = 32'd10;
        b = 32'd5;
        alu_control = 3'b000;
        #10;
        $display("Addition:      %d + %d = %d,\tOverflow: %b, Carry: %b", a, b, result, overflow, carry);
        
        // Test case 2: Subtraction (alu_control = 001)
        a = 32'd10;
        b = 32'd5;
        alu_control = 3'b001;
        #10;
        $display("Subtraction:   %d - %d = %d,\tOverflow: %b, Carry: %b", a, b, result, overflow, carry);
        
        // Test case 3: AND operation (alu_control = 010)
        a = 32'hF0F0;
        b = 32'hFF00;
        alu_control = 3'b010;
        #10;
        $display("AND:           0x%h & 0x%h = 0x%h,\tOverflow: %b, Carry: %b", a, b, result, overflow, carry);
        
        // Test case 4: XOR operation (alu_control = 011)
        a = 32'hF0F0;
        b = 32'hFF00;
        alu_control = 3'b011;
        #10;
        $display("XOR:           0x%h ^ 0x%h = 0x%h,\tOverflow: %b, Carry: %b", a, b, result, overflow, carry);
        
        // Test case 5: Set Less Than (alu_control = 101)
        a = 32'd5;
        b = 32'd10;
        alu_control = 3'b101;
        #10;
        $display("SLT:           %d < %d = %d,\tOverflow: %b, Carry: %b", a, b, result, overflow, carry);
        
        // Test case 6: Overflow test
        a = 32'h7FFFFFFF; // Maximum positive 32-bit signed integer
        b = 32'd1;
        alu_control = 3'b000; // Addition to cause overflow
        #10;
        $display("Overflow test: 0x%h + 0x%h = 0x%h,\tOverflow: %b, Carry: %b", a, b, result, overflow, carry);

        // Test case 7: Overflow test for subtraction
        a = 32'h80000000; // Minimum negative 32-bit signed integer
        b = 32'd1;
        alu_control = 3'b001; // Subtraction to cause overflow
        #10;
        $display("Overflow test (sub): 0x%h - 0x%h = 0x%h,\tOverflow: %b, Carry: %b", a, b, result, overflow, carry);
        
        // Test case 8: SLT with equal numbers
        a = 32'd10;
        b = 32'd10;
        alu_control = 3'b101;
        #10;
        $display("SLT (equal):   %d < %d = %d,\tOverflow: %b, Carry: %b", a, b, result, overflow, carry);

        // Test case 9: SLT with negative number
        a = 32'hFFFFFFFB; // -5
        b = 32'd10;
        alu_control = 3'b101;
        #10;
        // The reason for using $signed is to interpret the numbers as signed integers
        $display("SLT (negative): %d < %d = %d,\tOverflow: %b, Carry: %b", $signed(a), b, result, overflow, carry); 

        // Test case 10: Carry test for addition
        a = 32'hFFFFFFFF;
        b = 32'd1;
        alu_control = 3'b000;
        #10;
        $display("Carry test: 0x%h + 0x%h = 0x%h,\tOverflow: %b, Carry: %b", a, b, result, overflow, carry);
        // End simulation
        
        #10;
        $finish;
    end
endmodule

// Compile and run the testbench using the following commands:
// iverilog -o alu_tb alu.v alu_tb.v fulladder_32bit.v and_32bit.v xor_32bit.v slt_32bit.v mux_2x1_32bit.v mux_5x1_32bit.v zeroextender_32bit.v
// vvp alu_tb
// gtkwave

computer-organization/alu-design/alu/alu.vcd
$date
	Wed Apr 16 19:05:09 2025
$end
$version
	Icarus Verilog
$end
$timescale
	1s
$end
$scope module alu_tb $end
$var wire 32 ! result [31:0] $end
$var wire 1 " overflow $end
$var wire 1 # carry $end
$var reg 32 $ a [31:0] $end
$var reg 3 % alu_control [2:0] $end
$var reg 32 & b [31:0] $end
$scope module uut $end
$var wire 32 ' a [31:0] $end
$var wire 3 ( alu_control [2:0] $end
$var wire 32 ) b [31:0] $end
$var wire 32 * b_inverted [31:0] $end
$var wire 1 + cin_for_sub $end
$var wire 32 , xor_result [31:0] $end
$var wire 1 - sum_msb $end
$var wire 32 . sub_result [31:0] $end
$var wire 1 / slt_result $end
$var wire 32 0 slt_extended [31:0] $end
$var wire 32 1 result [31:0] $end
$var wire 1 " overflow $end
$var wire 1 2 msb_b $end
$var wire 1 3 msb_a $end
$var wire 1 4 cout_sub $end
$var wire 1 5 cout_add $end
$var wire 1 # carry $end
$var wire 32 6 and_result [31:0] $end
$var wire 32 7 add_result [31:0] $end
$scope module adder $end
$var wire 32 8 a [31:0] $end
$var wire 32 9 b [31:0] $end
$var wire 1 : cin $end
$var wire 33 ; temp_sum [32:0] $end
$var wire 32 < sum [31:0] $end
$var wire 1 5 cout $end
$upscope $end
$scope module and_op $end
$var wire 32 = a [31:0] $end
$var wire 32 > b [31:0] $end
$var wire 32 ? result [31:0] $end
$upscope $end
$scope module result_mux $end
$var wire 32 @ add_result [31:0] $end
$var wire 32 A and_result [31:0] $end
$var wire 3 B select [2:0] $end
$var wire 32 C xor_result [31:0] $end
$var wire 32 D sub_result [31:0] $end
$var wire 32 E slt_result [31:0] $end
$var reg 32 F result [31:0] $end
$upscope $end
$scope module slt_extender $end
$var wire 32 G o [31:0] $end
$var wire 1 / i $end
$upscope $end
$scope module slt_op $end
$var wire 1 H and_3_out $end
$var wire 1 I ctrl0 $end
$var wire 1 J ctrl1 $end
$var wire 1 3 msb_a $end
$var wire 1 2 msb_b $end
$var wire 1 K not_ctrl1 $end
$var wire 1 " overflow $end
$var wire 1 / slt_result $end
$var wire 1 - sum_msb $end
$var wire 1 L xnor_3_out $end
$var wire 1 M xor1_out $end
$upscope $end
$scope module subtractor $end
$var wire 32 N a [31:0] $end
$var wire 32 O b [31:0] $end
$var wire 1 + cin $end
$var wire 33 P temp_sum [32:0] $end
$var wire 32 Q sum [31:0] $end
$var wire 1 4 cout $end
$upscope $end
$scope module xor_op $end
$var wire 32 R a [31:0] $end
$var wire 32 S b [31:0] $end
$var wire 32 T result [31:0] $end
$upscope $end
$upscope $end
$upscope $end
$enddefinitions $end
$comment Show the parameter values. $end
$dumpall
$end
#0
$dumpvars
b0 T
b0 S
b0 R
b0 Q
b100000000000000000000000000000000 P
b11111111111111111111111111111111 O
b0 N
0M
1L
1K
0J
0I
0H
b0 G
b0 F
b0 E
b0 D
b0 C
b0 B
b0 A
b0 @
b0 ?
b0 >
b0 =
b0 <
b0 ;
0:
b0 9
b0 8
b0 7
b0 6
05
14
03
02
b0 1
b0 0
0/
b0 .
0-
b0 ,
1+
b11111111111111111111111111111111 *
b0 )
b0 (
b0 '
b0 &
b0 %
b0 $
0#
0"
b0 !
$end
#10
b1111 !
b1111 1
b1111 F
b11111111111111111111111111111010 *
b11111111111111111111111111111010 O
b1111 7
b1111 <
b1111 @
b101 .
b101 D
b101 Q
b1111 ,
b1111 C
b1111 T
b101 &
b101 )
b101 9
b101 >
b101 S
b1111 ;
b100000000000000000000000000000101 P
b1010 $
b1010 '
b1010 8
b1010 =
b1010 N
b1010 R
#20
0L
1I
1#
b101 !
b101 1
b101 F
b1 %
b1 (
b1 B
#30
1M
b1 0
b1 E
b1 G
1/
1-
1L
0K
0#
04
0I
1J
b1111000000000000 !
b1111000000000000 1
b1111000000000000 F
b11111111111111110000000011111111 *
b11111111111111110000000011111111 O
b11110111111110000 7
b11110111111110000 <
b11110111111110000 @
b1111000000000000 6
b1111000000000000 ?
b1111000000000000 A
b11111111111111111111000111110000 .
b11111111111111111111000111110000 D
b11111111111111111111000111110000 Q
b111111110000 ,
b111111110000 C
b111111110000 T
b10 %
b10 (
b10 B
b1111111100000000 &
b1111111100000000 )
b1111111100000000 9
b1111111100000000 >
b1111111100000000 S
b11110111111110000 ;
b11111111111111111111000111110000 P
b1111000011110000 $
b1111000011110000 '
b1111000011110000 8
b1111000011110000 =
b1111000011110000 N
b1111000011110000 R
#40
0L
1I
b111111110000 !
b111111110000 1
b111111110000 F
b11 %
b11 (
b11 B
#50
1K
0J
b1 !
b1 1
b1 F
b11111111111111111111111111110101 *
b11111111111111111111111111110101 O
b1111 7
b1111 <
b1111 @
b0 6
b0 ?
b0 A
b11111111111111111111111111111011 .
b11111111111111111111111111111011 D
b11111111111111111111111111111011 Q
b1111 ,
b1111 C
b1111 T
b101 %
b101 (
b101 B
b1010 &
b1010 )
b1010 9
b1010 >
b1010 S
b1111 ;
b11111111111111111111111111111011 P
b101 $
b101 '
b101 8
b101 =
b101 N
b101 R
#60
1"
1H
1L
1M
b0 0
b0 E
b0 G
0/
1-
0I
b10000000000000000000000000000000 !
b10000000000000000000000000000000 1
b10000000000000000000000000000000 F
b11111111111111111111111111111110 *
b11111111111111111111111111111110 O
b10000000000000000000000000000000 7
b10000000000000000000000000000000 <
b10000000000000000000000000000000 @
b1 6
b1 ?
b1 A
b1111111111111111111111111111110 .
b1111111111111111111111111111110 D
b1111111111111111111111111111110 Q
14
b1111111111111111111111111111110 ,
b1111111111111111111111111111110 C
b1111111111111111111111111111110 T
b0 %
b0 (
b0 B
b1 &
b1 )
b1 9
b1 >
b1 S
b10000000000000000000000000000000 ;
b101111111111111111111111111111110 P
b1111111111111111111111111111111 $
b1111111111111111111111111111111 '
b1111111111111111111111111111111 8
b1111111111111111111111111111111 =
b1111111111111111111111111111111 N
b1111111111111111111111111111111 R
#70
b1 0
b1 E
b1 G
1/
0-
1I
1#
b1111111111111111111111111111111 !
b1111111111111111111111111111111 1
b1111111111111111111111111111111 F
13
b10000000000000000000000000000001 7
b10000000000000000000000000000001 <
b10000000000000000000000000000001 @
b0 6
b0 ?
b0 A
b1111111111111111111111111111111 .
b1111111111111111111111111111111 D
b1111111111111111111111111111111 Q
b10000000000000000000000000000001 ,
b10000000000000000000000000000001 C
b10000000000000000000000000000001 T
b1 %
b1 (
b1 B
b10000000000000000000000000000001 ;
b101111111111111111111111111111111 P
b10000000000000000000000000000000 $
b10000000000000000000000000000000 '
b10000000000000000000000000000000 8
b10000000000000000000000000000000 =
b10000000000000000000000000000000 N
b10000000000000000000000000000000 R
#80
b0 0
b0 E
b0 G
0/
0L
0"
0H
0#
0M
b0 !
b0 1
b0 F
b11111111111111111111111111110101 *
b11111111111111111111111111110101 O
03
b10100 7
b10100 <
b10100 @
b1010 6
b1010 ?
b1010 A
b0 .
b0 D
b0 Q
b0 ,
b0 C
b0 T
b101 %
b101 (
b101 B
b1010 &
b1010 )
b1010 9
b1010 >
b1010 S
b10100 ;
b100000000000000000000000000000000 P
b1010 $
b1010 '
b1010 8
b1010 =
b1010 N
b1010 R
#90
b1 !
b1 1
b1 F
1L
b1 0
b1 E
b1 G
1/
1-
0M
13
b101 7
b101 <
b101 @
15
b11111111111111111111111111110001 .
b11111111111111111111111111110001 D
b11111111111111111111111111110001 Q
b11111111111111111111111111110001 ,
b11111111111111111111111111110001 C
b11111111111111111111111111110001 T
b100000000000000000000000000000101 ;
b111111111111111111111111111110001 P
b11111111111111111111111111111011 $
b11111111111111111111111111111011 '
b11111111111111111111111111111011 8
b11111111111111111111111111111011 =
b11111111111111111111111111111011 N
b11111111111111111111111111111011 R
#100
0L
1M
b0 0
b0 E
b0 G
0/
0-
0I
1#
b0 !
b0 1
b0 F
b11111111111111111111111111111110 *
b11111111111111111111111111111110 O
b0 7
b0 <
b0 @
b1 6
b1 ?
b1 A
b11111111111111111111111111111110 .
b11111111111111111111111111111110 D
b11111111111111111111111111111110 Q
b11111111111111111111111111111110 ,
b11111111111111111111111111111110 C
b11111111111111111111111111111110 T
b0 %
b0 (
b0 B
b1 &
b1 )
b1 9
b1 >
b1 S
b100000000000000000000000000000000 ;
b111111111111111111111111111111110 P
b11111111111111111111111111111111 $
b11111111111111111111111111111111 '
b11111111111111111111111111111111 8
b11111111111111111111111111111111 =
b11111111111111111111111111111111 N
b11111111111111111111111111111111 R
